meu_pacote/minha_lib.py
meu_pacote_teste-0.1.0.dist-info/METADATA
meu_pacote_teste-0.1.0.dist-info/WHEEL
meu_pacote_teste-0.1.0.dist-info/top_level.txt
meu_pacote_teste-0.1.0.dist-info/RECORD
