Metadata-Version: 2.1
Name: meu-pacote-teste
Version: 0.1.0
Summary: Teste de setuptools
Home-page: UNKNOWN
Author: Anthony Jatobá
Author-email: anthonyjatoba@gmail.com
License: UNKNOWN
Platform: UNKNOWN
